poit/__init__.py
poit/poit.py
poit-0.1.5.dist-info/WHEEL
poit-0.1.5.dist-info/METADATA
poit-0.1.5.dist-info/RECORD
