Metadata-Version: 2.1
Name: poit
Version: 0.1.5
Summary: Fetch information from POIT, The Official Swedish Gazette
Author: Johan Magnusson
Author-email: jcmmagnusson@gmail.com
Requires-Python: >=3.9,<4.0
Classifier: Programming Language :: Python :: 3
Classifier: Programming Language :: Python :: 3.9
Requires-Dist: beautifulsoup4 (>=4.9.3,<5.0.0)
Requires-Dist: requests (>=2.25.1,<3.0.0)
